pyopencnam.py
PyOpenCNAM-1.2.4.dist-info/LICENSE
PyOpenCNAM-1.2.4.dist-info/METADATA
PyOpenCNAM-1.2.4.dist-info/WHEEL
PyOpenCNAM-1.2.4.dist-info/top_level.txt
PyOpenCNAM-1.2.4.dist-info/zip-safe
PyOpenCNAM-1.2.4.dist-info/RECORD
