Metadata-Version: 2.1
Name: PyOpenCNAM
Version: 1.2.4
Summary: Get cnam info from phone numbers from opencnam.
Home-page: https://github.com/GameMaker2k/PyOpenCNAM
Download-URL: https://github.com/GameMaker2k/PyOpenCNAM/archive/master.tar.gz
Author: Kazuki Przyborowski
Author-email: kazuki.przyborowski@gmail.com
Maintainer: Kazuki Przyborowski
Maintainer-email: kazuki.przyborowski@gmail.com
License: Revised BSD License
Keywords: opencnam pyopencnam python python-opencnam
Platform: OS Independent
Classifier: Development Status :: 5 - Production/Stable
Classifier: Intended Audience :: Developers
Classifier: Intended Audience :: Other Audience
Classifier: License :: OSI Approved
Classifier: License :: OSI Approved :: BSD License
Classifier: Natural Language :: English
Classifier: Operating System :: MacOS
Classifier: Operating System :: MacOS :: MacOS X
Classifier: Operating System :: Microsoft
Classifier: Operating System :: Microsoft :: Windows
Classifier: Operating System :: OS/2
Classifier: Operating System :: OS Independent
Classifier: Operating System :: POSIX
Classifier: Operating System :: Unix
Classifier: Programming Language :: Python
Classifier: Topic :: Utilities
Classifier: Topic :: Software Development
Classifier: Topic :: Software Development :: Libraries
Classifier: Topic :: Software Development :: Libraries :: Python Modules
License-File: LICENSE
